.coveragerc
.editorconfig
.gitignore
.travis.yml
AUTHORS
CHANGELOG.rst
CONTRIBUTING.md
LICENSE
MANIFEST.in
Makefile
README.md
requirements.txt
requirements_dev.txt
setup.cfg
setup.py
tox.ini
apparmor.d/sbin.dhcpcanon
dhcpcanon/__init__.py
dhcpcanon/_version.py
dhcpcanon/clientscript.py
dhcpcanon/conflog.py
dhcpcanon/constants.py
dhcpcanon/dhcpcanon.py
dhcpcanon/dhcpcap.py
dhcpcanon/dhcpcapfsm.py
dhcpcanon/dhcpcaplease.py
dhcpcanon/dhcpcaputils.py
dhcpcanon/netutils.py
dhcpcanon/timers.py
dhcpcanon.egg-info/PKG-INFO
dhcpcanon.egg-info/SOURCES.txt
dhcpcanon.egg-info/dependency_links.txt
dhcpcanon.egg-info/entry_points.txt
dhcpcanon.egg-info/not-zip-safe
dhcpcanon.egg-info/requires.txt
dhcpcanon.egg-info/top_level.txt
docs/Makefile
docs/make.bat
docs/source/about.rst
docs/source/api.rst
docs/source/conf.py
docs/source/contributing.rst
docs/source/diagrams.rst
docs/source/download.rst
docs/source/implementation.rst
docs/source/index.rst
docs/source/install.rst
docs/source/install_run_cases.rst
docs/source/integration.rst
docs/source/privileges.rst
docs/source/questions.rst
docs/source/running.rst
docs/source/soa.rst
docs/source/specification.rst
docs/source/todo.rst
docs/source/images/calls_dhcpcanon.svg
docs/source/images/classes_dhcpcanon.svg
docs/source/images/dhcpcapfsm.svg
docs/source/images/organigram_dhcpcanon.svg
docs/source/images/packages_dhcpcanon.svg
man/dhcpcanon-script.8
man/dhcpcanon.8
sbin/dhcpcanon-script
systemd/dhcpcanon.service
systemd/network/90-dhcpcanon.link
tests/conftest.py
tests/dhcpcap_leases.py
tests/dhcpcap_objs.py
tests/dhcpcap_pkts.py
tests/dhcpcapfsm_objs.py
tests/test_dhcpcap.py
tests/test_dhcpcapfsm.py
tmpfiles.d/dhcpcanon.conf