Metadata-Version: 1.2
Name: dhcpcanon
Version: 0.8.1
Summary: DHCP client disclosing less identifying information
Home-page: https://github.com/juga0/dhcpcanon
Author: juga
Author-email: juga@riseup.net
License: MIT
Keywords: python scapy dhcp RFC7844 RFC2131 anonymity
Platform: UNKNOWN
Classifier: Development Status :: 3 - Alpha
Classifier: Environment :: Console
Classifier: Intended Audience :: End Users/Desktop
Classifier: Intended Audience :: Developers
Classifier: License :: OSI Approved :: MIT License
Classifier: Operating System :: OS Independent
Classifier: Programming Language :: Python :: 3
Classifier: Topic :: System :: Networking
Requires-Python: >=3.5
